README.rst
setup.py
itemid/__init__.py
itemid.egg-info/PKG-INFO
itemid.egg-info/SOURCES.txt
itemid.egg-info/dependency_links.txt
itemid.egg-info/requires.txt
itemid.egg-info/top_level.txt