Metadata-Version: 1.1
Name: itemid
Version: 0.8.20
Summary: A Library for shortening integers into abitrary set of characters
Home-page: https://bitbucket.org/rit/itemid
Author: Rit Li
Author-email: rit@quietdynamite.com
License: MIT
Keywords: url shortening product id
Platform: UNKNOWN
Classifier: Development Status :: 5 - Production/Stable
Classifier: Intended Audience :: Developers
Classifier: Topic :: Software Development :: Build Tools
Classifier: License :: OSI Approved :: MIT License
Classifier: Programming Language :: Python :: 2.7
